LICENSE
MANIFEST.in
README.md
pyproject.toml
setup.py
survivalist/__init__.py
survivalist/base.py
survivalist/column.py
survivalist/compare.py
survivalist/exceptions.py
survivalist/functions.py
survivalist/metrics.py
survivalist/nonparametric.py
survivalist/preprocessing.py
survivalist/testing.py
survivalist/util.py
survivalist.egg-info/PKG-INFO
survivalist.egg-info/SOURCES.txt
survivalist.egg-info/dependency_links.txt
survivalist.egg-info/requires.txt
survivalist.egg-info/top_level.txt
survivalist/coxml/__init__.py
survivalist/coxml/coxmlcode.py
survivalist/custom/__init__.py
survivalist/custom/confcustom.py
survivalist/custom/custom.py
survivalist/datasets/__init__.py
survivalist/datasets/base.py
survivalist/datasets/data/GBSG2.arff
survivalist/datasets/data/actg320.arff
survivalist/datasets/data/breast_cancer_GSE7390-metastasis.arff
survivalist/datasets/data/flchain.arff
survivalist/datasets/data/veteran.arff
survivalist/datasets/data/whas500.arff
survivalist/ensemble/__init__.py
survivalist/ensemble/_coxph_loss.pyx
survivalist/ensemble/boosting.py
survivalist/ensemble/confgenboosting.py
survivalist/ensemble/genboosting.py
survivalist/ensemble/survival_loss.py
survivalist/io/__init__.py
survivalist/io/arffread.py
survivalist/io/arffwrite.py
survivalist/linear_model/__init__.py
survivalist/linear_model/coxph.py
survivalist/meta/__init__.py
survivalist/meta/base.py
survivalist/meta/ensemble_selection.py
survivalist/meta/stacking.py
survivalist/survstack/__init__.py
survivalist/survstack/functional.py
survivalist/survstack/survstacker.py
survivalist/survstack/transformer.py
survivalist/utils/__init__.py
survivalist/utils/simulation.py
tests/test_aft.py
tests/test_binarytrees.py
tests/test_boosting.py
tests/test_clinical_kernel.py
tests/test_column.py
tests/test_common.py
tests/test_compare.py
tests/test_coxnet.py
tests/test_coxph.py
tests/test_datasets.py
tests/test_ensemble_selection.py
tests/test_forest.py
tests/test_functions.py
tests/test_io.py
tests/test_metrics.py
tests/test_minlip.py
tests/test_nonparametric.py
tests/test_pandas_inputs.py
tests/test_preprocessing.py
tests/test_show_versions.py
tests/test_stacking.py
