Metadata-Version: 2.4
Name: survivalist
Version: 0.3.3
Summary: Survival analysis built on top of scikit-learn
Author-email: "T. Moudiki" <thierry.moudiki@gmail.com>
License: The Clear BSD License
Project-URL: Homepage, https://techtonique.github.io/survivalist
Project-URL: Documentation, https://techtonique.github.io/survivalist
Project-URL: Source Code, https://github.com/Techtonique/survivalist
Project-URL: Bug Tracker, https://github.com/Techtonique/survivalist/issues
Project-URL: Release Notes, https://github.com/Techtonique/survivalist/releases
Classifier: Development Status :: 4 - Beta
Classifier: Intended Audience :: Science/Research
Classifier: Intended Audience :: Developers
Classifier: License :: OSI Approved :: BSD License
Classifier: Operating System :: MacOS
Classifier: Operating System :: Microsoft :: Windows
Classifier: Operating System :: POSIX
Classifier: Programming Language :: C++
Classifier: Programming Language :: Cython
Classifier: Programming Language :: Python
Classifier: Programming Language :: Python :: 3
Classifier: Programming Language :: Python :: 3.10
Classifier: Programming Language :: Python :: 3.11
Classifier: Programming Language :: Python :: 3.12
Classifier: Programming Language :: Python :: 3.13
Classifier: Topic :: Software Development
Classifier: Topic :: Scientific/Engineering
Requires-Python: >=3.10
License-File: LICENSE
Requires-Dist: ecos
Requires-Dist: joblib
Requires-Dist: numexpr
Requires-Dist: numpy
Requires-Dist: osqp!=0.6.0,!=0.6.1
Requires-Dist: pandas>=1.4.0
Requires-Dist: scipy>=1.3.2
Requires-Dist: scikit-learn<1.7,>=1.4.0
Requires-Dist: nnetsauce
Provides-Extra: dev
Requires-Dist: black[jupyter]; extra == "dev"
Requires-Dist: build; extra == "dev"
Requires-Dist: coverage; extra == "dev"
Requires-Dist: Cython>=3.0.10; extra == "dev"
Requires-Dist: packaging; extra == "dev"
Requires-Dist: pre-commit; extra == "dev"
Requires-Dist: pytest; extra == "dev"
Requires-Dist: ruff; extra == "dev"
Requires-Dist: setuptools-scm>=8; extra == "dev"
Requires-Dist: tomli; extra == "dev"
Requires-Dist: tox; extra == "dev"
Provides-Extra: docs
Requires-Dist: ipython!=8.7.0; extra == "docs"
Requires-Dist: nbsphinx>=0.9.2; extra == "docs"
Requires-Dist: docutils; extra == "docs"
Requires-Dist: setuptools-scm; extra == "docs"
Requires-Dist: sphinx~=7.3.7; extra == "docs"
Requires-Dist: pydata-sphinx-theme~=0.15.2; extra == "docs"
Requires-Dist: sphinxcontrib-spelling; extra == "docs"
Requires-Dist: sphinx-design~=0.5.0; extra == "docs"
Requires-Dist: sphinx-copybutton~=0.5.2; extra == "docs"
Provides-Extra: nbval
Requires-Dist: ipykernel; extra == "nbval"
Requires-Dist: ipython!=8.7.0; extra == "nbval"
Requires-Dist: matplotlib~=3.9.0; extra == "nbval"
Requires-Dist: nbformat; extra == "nbval"
Requires-Dist: nbval>=0.10.0; extra == "nbval"
Requires-Dist: seaborn~=0.13.2; extra == "nbval"
Dynamic: license-file
